{
  "summary": {
    "total_passes": 15,
    "active_passes": 6,
    "enabled_passes": 2,
    "expanded_passes": 6,
    "inactive_passes": 7,
    "tested_prefix_pairs": 84,
    "activation_edges": 4,
    "expansion_edges": 18,
    "mutation_edges": 2,
    "enable_edges": 24
  },
  "active_passes": [
    "early-cse",
    "gvn",
    "indvars",
    "instcombine",
    "licm",
    "loop-unroll"
  ],
  "enabled_passes": [
    "loop-rotate",
    "simplifycfg"
  ],
  "expanded_passes": [
    "early-cse",
    "gvn",
    "indvars",
    "instcombine",
    "licm",
    "loop-unroll"
  ],
  "inactive_passes": [
    "adce",
    "dce",
    "loop-simplify",
    "mem2reg",
    "reassociate",
    "sccp",
    "sroa"
  ],
  "edges": [
    {
      "edge_kind": "mutation",
      "enabler": "instcombine",
      "enabled": "gvn",
      "round": 1,
      "prefix": [
        "instcombine"
      ],
      "reads_after_prefix": [
        "inst:Bubble:%11",
        "inst:Bubble:%13",
        "inst:Bubble:%14",
        "inst:Bubble:%15",
        "inst:Bubble:%17",
        "inst:Bubble:%18",
        "inst:Bubble:%21",
        "inst:Bubble:%22",
        "inst:Bubble:%23",
        "inst:Bubble:%24",
        "inst:Bubble:%25",
        "inst:Bubble:%3",
        "inst:Bubble:%4"
      ],
      "writes_after_prefix": [
        "inst:Bubble:%.pre",
        "inst:Bubble:%10",
        "inst:Bubble:%11",
        "inst:Bubble:%12",
        "inst:Bubble:%13",
        "inst:Bubble:%14",
        "inst:Bubble:%15",
        "inst:Bubble:%16",
        "inst:Bubble:%17",
        "inst:Bubble:%18",
        "inst:Bubble:%19",
        "inst:Bubble:%21",
        "inst:Bubble:%22",
        "inst:Bubble:%23",
        "inst:Bubble:%24",
        "inst:Bubble:%25",
        "inst:Bubble:%26",
        "inst:Bubble:%3",
        "inst:Bubble:%4"
      ],
      "new_writes_after_prefix": [],
      "changed_writes_after_prefix": [
        "inst:Bubble:%12",
        "inst:Bubble:%13",
        "inst:Bubble:%14"
      ]
    },
    {
      "edge_kind": "activation",
      "enabler": "instcombine",
      "enabled": "loop-rotate",
      "round": 1,
      "prefix": [
        "instcombine"
      ],
      "reads_after_prefix": [],
      "writes_after_prefix": [
        "inst:Bubble:%indvars.iv.next3.lcssa"
      ],
      "new_writes_after_prefix": [
        "inst:Bubble:%indvars.iv.next3.lcssa"
      ],
      "changed_writes_after_prefix": []
    },
    {
      "edge_kind": "mutation",
      "enabler": "instcombine",
      "enabled": "indvars",
      "round": 1,
      "prefix": [
        "instcombine"
      ],
      "reads_after_prefix": [
        "inst:Bubble:%11",
        "inst:Bubble:%13"
      ],
      "writes_after_prefix": [
        "inst:Bubble:%11",
        "inst:Bubble:%13"
      ],
      "new_writes_after_prefix": [],
      "changed_writes_after_prefix": [
        "inst:Bubble:%11",
        "inst:Bubble:%13"
      ]
    },
    {
      "edge_kind": "expansion",
      "enabler": "instcombine",
      "enabled": "loop-unroll",
      "round": 1,
      "prefix": [
        "instcombine"
      ],
      "reads_after_prefix": [
        "inst:Bubble:%11",
        "inst:Bubble:%13",
        "inst:Bubble:%14",
        "inst:Bubble:%15",
        "inst:Bubble:%17",
        "inst:Bubble:%18",
        "inst:Bubble:%21",
        "inst:Bubble:%22",
        "inst:Bubble:%23",
        "inst:Bubble:%24",
        "inst:Bubble:%25",
        "inst:Bubble:%3",
        "inst:Bubble:%4",
        "inst:Bubble:%5",
        "inst:Bubble:%6",
        "inst:Bubble:%7",
        "inst:Bubble:%exitcond.not",
        "inst:Bubble:.preheader:1:br",
        "inst:Bubble:bb2:1:br",
        "inst:Bubble:bb3:1:br",
        "inst:Bubble:bb4:1:store",
        "inst:Bubble:bb4:2:br",
        "inst:Bubble:bb5:1:br",
        "inst:Bubble:bb6:1:br",
        "inst:Bubble:bb7:1:ret",
        "loop:Bubble:.preheader",
        "loop:Bubble:bb3"
      ],
      "writes_after_prefix": [
        "bb:Bubble:.epil.preheader",
        "bb:Bubble:.epilog-lcssa",
        "bb:Bubble:.preheader.new",
        "bb:Bubble:.unr-lcssa",
        "bb:Bubble:bb10",
        "bb:Bubble:bb11",
        "bb:Bubble:bb8",
        "bb:Bubble:bb9",
        "inst:Bubble:%10",
        "inst:Bubble:%11",
        "inst:Bubble:%13",
        "inst:Bubble:%14",
        "inst:Bubble:%15",
        "inst:Bubble:%16",
        "inst:Bubble:%17",
        "inst:Bubble:%18",
        "inst:Bubble:%2",
        "inst:Bubble:%21",
        "inst:Bubble:%22",
        "inst:Bubble:%23",
        "inst:Bubble:%24",
        "inst:Bubble:%25",
        "inst:Bubble:%26",
        "inst:Bubble:%29",
        "inst:Bubble:%3",
        "inst:Bubble:%31",
        "inst:Bubble:%32",
        "inst:Bubble:%33",
        "inst:Bubble:%35",
        "inst:Bubble:%36",
        "inst:Bubble:%39",
        "inst:Bubble:%4",
        "inst:Bubble:%40",
        "inst:Bubble:%41",
        "inst:Bubble:%42",
        "inst:Bubble:%43",
        "inst:Bubble:%5",
        "inst:Bubble:%6",
        "inst:Bubble:%7",
        "inst:Bubble:%8",
        "inst:Bubble:%9",
        "inst:Bubble:%exitcond.not",
        "inst:Bubble:%indvar",
        "inst:Bubble:%indvar.next",
        "inst:Bubble:%indvars.iv.next.1",
        "inst:Bubble:%indvars.iv.next.epil",
        "inst:Bubble:%indvars.iv.next3.lcssa",
        "inst:Bubble:%indvars.iv1.epil.init",
        "inst:Bubble:%indvars.iv1.unr",
        "inst:Bubble:%lcmp.mod",
        "inst:Bubble:%lcmp.mod1",
        "inst:Bubble:%niter",
        "inst:Bubble:%niter.ncmp.1",
        "inst:Bubble:%niter.next.1",
        "inst:Bubble:%unroll_iter",
        "inst:Bubble:%xtraiter",
        "inst:Bubble:.epil.preheader:1:call",
        "inst:Bubble:.epil.preheader:2:br",
        "inst:Bubble:.epilog-lcssa:1:br",
        "inst:Bubble:.preheader.new:1:br",
        "inst:Bubble:.preheader:1:br",
        "inst:Bubble:.unr-lcssa:1:br",
        "inst:Bubble:bb10:1:br",
        "inst:Bubble:bb11:1:ret",
        "inst:Bubble:bb2:1:br",
        "inst:Bubble:bb3:1:br",
        "inst:Bubble:bb3:1:store",
        "inst:Bubble:bb3:2:store",
        "inst:Bubble:bb3:3:br",
        "inst:Bubble:bb4:1:br",
        "inst:Bubble:bb4:1:store",
        "inst:Bubble:bb4:2:br",
        "inst:Bubble:bb5:1:br",
        "inst:Bubble:bb6:1:br",
        "inst:Bubble:bb7:1:ret",
        "inst:Bubble:bb7:1:store",
        "inst:Bubble:bb7:2:store",
        "inst:Bubble:bb7:3:br",
        "inst:Bubble:bb8:1:store",
        "inst:Bubble:bb8:2:br",
        "inst:Bubble:bb9:1:br",
        "loop:Bubble:.preheader",
        "loop:Bubble:.unr-lcssa",
        "loop:Bubble:bb3"
      ],
      "new_writes_after_prefix": [
        "inst:Bubble:%13",
        "inst:Bubble:%31",
        "inst:Bubble:%exitcond.not",
        "inst:Bubble:%indvars.iv.next3.lcssa",
        "loop:Bubble:.unr-lcssa",
        "loop:Bubble:bb3"
      ],
      "changed_writes_after_prefix": [
        "inst:Bubble:%29",
        "inst:Bubble:%niter.ncmp.1"
      ]
    },
    {
      "edge_kind": "activation",
      "enabler": "early-cse",
      "enabled": "loop-rotate",
      "round": 1,
      "prefix": [
        "early-cse"
      ],
      "reads_after_prefix": [],
      "writes_after_prefix": [
        "inst:Bubble:%.lcssa"
      ],
      "new_writes_after_prefix": [
        "inst:Bubble:%.lcssa"
      ],
      "changed_writes_after_prefix": []
    },
    {
      "edge_kind": "expansion",
      "enabler": "early-cse",
      "enabled": "loop-unroll",
      "round": 1,
      "prefix": [
        "early-cse"
      ],
      "reads_after_prefix": [
        "inst:Bubble:%11",
        "inst:Bubble:%12",
        "inst:Bubble:%14",
        "inst:Bubble:%15",
        "inst:Bubble:%17",
        "inst:Bubble:%18",
        "inst:Bubble:%21",
        "inst:Bubble:%22",
        "inst:Bubble:%23",
        "inst:Bubble:%24",
        "inst:Bubble:%25",
        "inst:Bubble:%3",
        "inst:Bubble:%4",
        "inst:Bubble:%5",
        "inst:Bubble:%6",
        "inst:Bubble:%7",
        "inst:Bubble:%exitcond",
        "inst:Bubble:.preheader:1:br",
        "inst:Bubble:bb2:1:br",
        "inst:Bubble:bb3:1:br",
        "inst:Bubble:bb4:1:store",
        "inst:Bubble:bb4:2:br",
        "inst:Bubble:bb5:1:br",
        "inst:Bubble:bb6:1:br",
        "inst:Bubble:bb7:1:ret",
        "loop:Bubble:.preheader",
        "loop:Bubble:bb0"
      ],
      "writes_after_prefix": [
        "bb:Bubble:.epil.preheader",
        "bb:Bubble:.epilog-lcssa",
        "bb:Bubble:.preheader.new",
        "bb:Bubble:.unr-lcssa",
        "bb:Bubble:bb10",
        "bb:Bubble:bb11",
        "bb:Bubble:bb8",
        "bb:Bubble:bb9",
        "inst:Bubble:%.lcssa",
        "inst:Bubble:%10",
        "inst:Bubble:%11",
        "inst:Bubble:%12",
        "inst:Bubble:%14",
        "inst:Bubble:%15",
        "inst:Bubble:%16",
        "inst:Bubble:%17",
        "inst:Bubble:%18",
        "inst:Bubble:%2",
        "inst:Bubble:%21",
        "inst:Bubble:%22",
        "inst:Bubble:%23",
        "inst:Bubble:%24",
        "inst:Bubble:%25",
        "inst:Bubble:%26",
        "inst:Bubble:%29",
        "inst:Bubble:%3",
        "inst:Bubble:%30",
        "inst:Bubble:%32",
        "inst:Bubble:%33",
        "inst:Bubble:%35",
        "inst:Bubble:%36",
        "inst:Bubble:%39",
        "inst:Bubble:%4",
        "inst:Bubble:%40",
        "inst:Bubble:%41",
        "inst:Bubble:%42",
        "inst:Bubble:%43",
        "inst:Bubble:%5",
        "inst:Bubble:%6",
        "inst:Bubble:%7",
        "inst:Bubble:%8",
        "inst:Bubble:%9",
        "inst:Bubble:%exitcond",
        "inst:Bubble:%indvar",
        "inst:Bubble:%indvar.next",
        "inst:Bubble:%indvars.iv.next.1",
        "inst:Bubble:%indvars.iv.next.epil",
        "inst:Bubble:%indvars.iv1.epil.init",
        "inst:Bubble:%indvars.iv1.unr",
        "inst:Bubble:%lcmp.mod",
        "inst:Bubble:%lcmp.mod1",
        "inst:Bubble:%niter",
        "inst:Bubble:%niter.ncmp.1",
        "inst:Bubble:%niter.next.1",
        "inst:Bubble:%unroll_iter",
        "inst:Bubble:%xtraiter",
        "inst:Bubble:.epil.preheader:1:call",
        "inst:Bubble:.epil.preheader:2:br",
        "inst:Bubble:.epilog-lcssa:1:br",
        "inst:Bubble:.preheader.new:1:br",
        "inst:Bubble:.preheader:1:br",
        "inst:Bubble:.unr-lcssa:1:br",
        "inst:Bubble:bb10:1:br",
        "inst:Bubble:bb11:1:ret",
        "inst:Bubble:bb2:1:br",
        "inst:Bubble:bb3:1:br",
        "inst:Bubble:bb3:1:store",
        "inst:Bubble:bb3:2:store",
        "inst:Bubble:bb3:3:br",
        "inst:Bubble:bb4:1:br",
        "inst:Bubble:bb4:1:store",
        "inst:Bubble:bb4:2:br",
        "inst:Bubble:bb5:1:br",
        "inst:Bubble:bb6:1:br",
        "inst:Bubble:bb7:1:ret",
        "inst:Bubble:bb7:1:store",
        "inst:Bubble:bb7:2:store",
        "inst:Bubble:bb7:3:br",
        "inst:Bubble:bb8:1:store",
        "inst:Bubble:bb8:2:br",
        "inst:Bubble:bb9:1:br",
        "loop:Bubble:.preheader",
        "loop:Bubble:bb0"
      ],
      "new_writes_after_prefix": [
        "inst:Bubble:%.lcssa"
      ],
      "changed_writes_after_prefix": []
    },
    {
      "edge_kind": "expansion",
      "enabler": "gvn",
      "enabled": "instcombine",
      "round": 1,
      "prefix": [
        "gvn"
      ],
      "reads_after_prefix": [
        "inst:Bubble:%12",
        "inst:Bubble:%13",
        "inst:Bubble:%5",
        "inst:Bubble:%6",
        "inst:Bubble:%7",
        "inst:Bubble:%exitcond",
        "inst:bInitarr:%exitcond",
        "inst:main:%exitcond",
        "loop:Bubble:bb0",
        "loop:bInitarr:bb0",
        "loop:main:bb0"
      ],
      "writes_after_prefix": [
        "inst:Bubble:%12",
        "inst:Bubble:%13",
        "inst:Bubble:%14",
        "inst:Bubble:%5",
        "inst:Bubble:%6",
        "inst:Bubble:%7",
        "inst:Bubble:%8",
        "inst:Bubble:%exitcond",
        "inst:Bubble:%exitcond.not",
        "inst:bInitarr:%exitcond",
        "inst:bInitarr:%exitcond.not",
        "inst:main:%exitcond",
        "inst:main:%exitcond.not",
        "loop:Bubble:bb0",
        "loop:Bubble:bb3",
        "loop:bInitarr:bb0",
        "loop:bInitarr:bb5",
        "loop:main:bb0",
        "loop:main:bb1"
      ],
      "new_writes_after_prefix": [
        "inst:Bubble:%14",
        "inst:Bubble:%5",
        "inst:Bubble:%6",
        "inst:Bubble:%7",
        "inst:Bubble:%8"
      ],
      "changed_writes_after_prefix": [
        "inst:Bubble:%12",
        "inst:Bubble:%13"
      ]
    },
    {
      "edge_kind": "activation",
      "enabler": "gvn",
      "enabled": "loop-rotate",
      "round": 1,
      "prefix": [
        "gvn"
      ],
      "reads_after_prefix": [],
      "writes_after_prefix": [
        "inst:Bubble:%.lcssa"
      ],
      "new_writes_after_prefix": [
        "inst:Bubble:%.lcssa"
      ],
      "changed_writes_after_prefix": []
    },
    {
      "edge_kind": "expansion",
      "enabler": "gvn",
      "enabled": "licm",
      "round": 1,
      "prefix": [
        "gvn"
      ],
      "reads_after_prefix": [
        "inst:Bubble:%12",
        "inst:Bubble:%13"
      ],
      "writes_after_prefix": [
        "inst:Bubble:%12",
        "inst:Bubble:%13",
        "inst:Bubble:%14",
        "inst:Bubble:%indvars.iv.next3.lcssa"
      ],
      "new_writes_after_prefix": [
        "inst:Bubble:%14"
      ],
      "changed_writes_after_prefix": [
        "inst:Bubble:%12",
        "inst:Bubble:%13"
      ]
    },
    {
      "edge_kind": "expansion",
      "enabler": "gvn",
      "enabled": "indvars",
      "round": 1,
      "prefix": [
        "gvn"
      ],
      "reads_after_prefix": [
        "inst:Bubble:%12",
        "inst:Bubble:%13",
        "inst:Bubble:%15",
        "inst:Bubble:%16",
        "inst:Bubble:%18",
        "inst:Bubble:%19",
        "inst:Bubble:%22",
        "inst:Bubble:%23",
        "inst:Bubble:%24",
        "inst:Bubble:%25",
        "inst:Bubble:%26",
        "inst:Bubble:bb4:1:store"
      ],
      "writes_after_prefix": [
        "inst:Bubble:%12",
        "inst:Bubble:%13",
        "inst:Bubble:%14",
        "inst:Bubble:%15",
        "inst:Bubble:%16",
        "inst:Bubble:%17",
        "inst:Bubble:%18",
        "inst:Bubble:%19",
        "inst:Bubble:%21",
        "inst:Bubble:%22",
        "inst:Bubble:%23",
        "inst:Bubble:%24",
        "inst:Bubble:%25",
        "inst:Bubble:%26",
        "inst:Bubble:bb4:1:store"
      ],
      "new_writes_after_prefix": [
        "inst:Bubble:%19",
        "inst:Bubble:%26"
      ],
      "changed_writes_after_prefix": [
        "inst:Bubble:%12",
        "inst:Bubble:%13",
        "inst:Bubble:%14",
        "inst:Bubble:%15",
        "inst:Bubble:%16",
        "inst:Bubble:%17",
        "inst:Bubble:%18",
        "inst:Bubble:%21",
        "inst:Bubble:%22",
        "inst:Bubble:%23",
        "inst:Bubble:%24",
        "inst:Bubble:%25"
      ]
    },
    {
      "edge_kind": "expansion",
      "enabler": "gvn",
      "enabled": "loop-unroll",
      "round": 1,
      "prefix": [
        "gvn"
      ],
      "reads_after_prefix": [
        "inst:Bubble:%10",
        "inst:Bubble:%12",
        "inst:Bubble:%13",
        "inst:Bubble:%15",
        "inst:Bubble:%16",
        "inst:Bubble:%18",
        "inst:Bubble:%19",
        "inst:Bubble:%22",
        "inst:Bubble:%23",
        "inst:Bubble:%24",
        "inst:Bubble:%26",
        "inst:Bubble:%3",
        "inst:Bubble:%4",
        "inst:Bubble:%5",
        "inst:Bubble:%6",
        "inst:Bubble:%7",
        "inst:Bubble:%exitcond",
        "inst:Bubble:.preheader:1:br",
        "inst:Bubble:bb2:1:br",
        "inst:Bubble:bb3:1:br",
        "inst:Bubble:bb4:1:store",
        "inst:Bubble:bb4:2:br",
        "inst:Bubble:bb5:1:br",
        "inst:Bubble:bb6:1:br",
        "inst:Bubble:bb7:1:ret",
        "loop:Bubble:.preheader",
        "loop:Bubble:bb0"
      ],
      "writes_after_prefix": [
        "bb:Bubble:.epil.preheader",
        "bb:Bubble:.epilog-lcssa",
        "bb:Bubble:.preheader.new",
        "bb:Bubble:.unr-lcssa",
        "bb:Bubble:bb10",
        "bb:Bubble:bb11",
        "bb:Bubble:bb8",
        "bb:Bubble:bb9",
        "inst:Bubble:%.epil.init",
        "inst:Bubble:%.lcssa",
        "inst:Bubble:%.unr",
        "inst:Bubble:%10",
        "inst:Bubble:%11",
        "inst:Bubble:%12",
        "inst:Bubble:%13",
        "inst:Bubble:%14",
        "inst:Bubble:%15",
        "inst:Bubble:%16",
        "inst:Bubble:%17",
        "inst:Bubble:%18",
        "inst:Bubble:%19",
        "inst:Bubble:%2",
        "inst:Bubble:%21",
        "inst:Bubble:%22",
        "inst:Bubble:%23",
        "inst:Bubble:%24",
        "inst:Bubble:%26",
        "inst:Bubble:%29",
        "inst:Bubble:%3",
        "inst:Bubble:%30",
        "inst:Bubble:%32",
        "inst:Bubble:%33",
        "inst:Bubble:%35",
        "inst:Bubble:%36",
        "inst:Bubble:%39",
        "inst:Bubble:%4",
        "inst:Bubble:%40",
        "inst:Bubble:%41",
        "inst:Bubble:%42",
        "inst:Bubble:%43",
        "inst:Bubble:%5",
        "inst:Bubble:%6",
        "inst:Bubble:%7",
        "inst:Bubble:%8",
        "inst:Bubble:%9",
        "inst:Bubble:%exitcond",
        "inst:Bubble:%indvar",
        "inst:Bubble:%indvar.next",
        "inst:Bubble:%indvars.iv.next.1",
        "inst:Bubble:%indvars.iv.next.epil",
        "inst:Bubble:%indvars.iv1.epil.init",
        "inst:Bubble:%indvars.iv1.unr",
        "inst:Bubble:%lcmp.mod",
        "inst:Bubble:%lcmp.mod1",
        "inst:Bubble:%niter",
        "inst:Bubble:%niter.ncmp.1",
        "inst:Bubble:%niter.next.1",
        "inst:Bubble:%unroll_iter",
        "inst:Bubble:%xtraiter",
        "inst:Bubble:.epil.preheader:1:call",
        "inst:Bubble:.epil.preheader:2:br",
        "inst:Bubble:.epilog-lcssa:1:br",
        "inst:Bubble:.preheader.new:1:br",
        "inst:Bubble:.preheader:1:br",
        "inst:Bubble:.unr-lcssa:1:br",
        "inst:Bubble:bb10:1:br",
        "inst:Bubble:bb11:1:ret",
        "inst:Bubble:bb2:1:br",
        "inst:Bubble:bb3:1:br",
        "inst:Bubble:bb3:1:store",
        "inst:Bubble:bb3:2:store",
        "inst:Bubble:bb3:3:br",
        "inst:Bubble:bb4:1:br",
        "inst:Bubble:bb4:1:store",
        "inst:Bubble:bb4:2:br",
        "inst:Bubble:bb5:1:br",
        "inst:Bubble:bb6:1:br",
        "inst:Bubble:bb7:1:ret",
        "inst:Bubble:bb7:1:store",
        "inst:Bubble:bb7:2:store",
        "inst:Bubble:bb7:3:br",
        "inst:Bubble:bb8:1:store",
        "inst:Bubble:bb8:2:br",
        "inst:Bubble:bb9:1:br",
        "loop:Bubble:.preheader",
        "loop:Bubble:bb0"
      ],
      "new_writes_after_prefix": [
        "inst:Bubble:%.epil.init",
        "inst:Bubble:%.lcssa",
        "inst:Bubble:%.unr",
        "inst:Bubble:%13",
        "inst:Bubble:%19"
      ],
      "changed_writes_after_prefix": [
        "inst:Bubble:%14",
        "inst:Bubble:%15",
        "inst:Bubble:%21",
        "inst:Bubble:%22",
        "inst:Bubble:%23",
        "inst:Bubble:%7",
        "inst:Bubble:%8"
      ]
    },
    {
      "edge_kind": "expansion",
      "enabler": "licm",
      "enabled": "instcombine",
      "round": 1,
      "prefix": [
        "licm"
      ],
      "reads_after_prefix": [
        "inst:Bubble:%11",
        "inst:Bubble:%exitcond",
        "inst:Bubble:%indvars.iv.next3.lcssa",
        "inst:bInitarr:%exitcond",
        "inst:main:%exitcond",
        "loop:Bubble:bb0",
        "loop:bInitarr:bb0",
        "loop:main:bb0"
      ],
      "writes_after_prefix": [
        "inst:Bubble:%11",
        "inst:Bubble:%exitcond",
        "inst:Bubble:%exitcond.not",
        "inst:Bubble:%indvars.iv.next3.lcssa",
        "inst:bInitarr:%exitcond",
        "inst:bInitarr:%exitcond.not",
        "inst:main:%exitcond",
        "inst:main:%exitcond.not",
        "loop:Bubble:bb0",
        "loop:Bubble:bb3",
        "loop:bInitarr:bb0",
        "loop:bInitarr:bb5",
        "loop:main:bb0",
        "loop:main:bb1"
      ],
      "new_writes_after_prefix": [
        "inst:Bubble:%indvars.iv.next3.lcssa"
      ],
      "changed_writes_after_prefix": []
    },
    {
      "edge_kind": "expansion",
      "enabler": "licm",
      "enabled": "early-cse",
      "round": 1,
      "prefix": [
        "licm"
      ],
      "reads_after_prefix": [
        "inst:Bubble:%indvars.iv.next3.lcssa"
      ],
      "writes_after_prefix": [
        "inst:Bubble:%indvars.iv.next3.lcssa"
      ],
      "new_writes_after_prefix": [
        "inst:Bubble:%indvars.iv.next3.lcssa"
      ],
      "changed_writes_after_prefix": []
    },
    {
      "edge_kind": "expansion",
      "enabler": "licm",
      "enabled": "gvn",
      "round": 1,
      "prefix": [
        "licm"
      ],
      "reads_after_prefix": [
        "inst:Bubble:%11",
        "inst:Bubble:%13",
        "inst:Bubble:%14",
        "inst:Bubble:%15",
        "inst:Bubble:%17",
        "inst:Bubble:%18",
        "inst:Bubble:%21",
        "inst:Bubble:%22",
        "inst:Bubble:%23",
        "inst:Bubble:%24",
        "inst:Bubble:%25",
        "inst:Bubble:%3",
        "inst:Bubble:%4",
        "inst:Bubble:%indvars.iv.next3.lcssa"
      ],
      "writes_after_prefix": [
        "inst:Bubble:%.pre",
        "inst:Bubble:%10",
        "inst:Bubble:%11",
        "inst:Bubble:%12",
        "inst:Bubble:%13",
        "inst:Bubble:%14",
        "inst:Bubble:%15",
        "inst:Bubble:%16",
        "inst:Bubble:%17",
        "inst:Bubble:%18",
        "inst:Bubble:%19",
        "inst:Bubble:%21",
        "inst:Bubble:%22",
        "inst:Bubble:%23",
        "inst:Bubble:%24",
        "inst:Bubble:%25",
        "inst:Bubble:%26",
        "inst:Bubble:%3",
        "inst:Bubble:%4",
        "inst:Bubble:%indvars.iv.next3.lcssa"
      ],
      "new_writes_after_prefix": [
        "inst:Bubble:%indvars.iv.next3.lcssa"
      ],
      "changed_writes_after_prefix": [
        "inst:Bubble:%12",
        "inst:Bubble:%13",
        "inst:Bubble:%14"
      ]
    },
    {
      "edge_kind": "expansion",
      "enabler": "licm",
      "enabled": "indvars",
      "round": 1,
      "prefix": [
        "licm"
      ],
      "reads_after_prefix": [
        "inst:Bubble:%13",
        "inst:Bubble:%indvars.iv.next3.lcssa"
      ],
      "writes_after_prefix": [
        "inst:Bubble:%13",
        "inst:Bubble:%indvars.iv.next3.lcssa"
      ],
      "new_writes_after_prefix": [
        "inst:Bubble:%indvars.iv.next3.lcssa"
      ],
      "changed_writes_after_prefix": [
        "inst:Bubble:%13"
      ]
    },
    {
      "edge_kind": "expansion",
      "enabler": "licm",
      "enabled": "loop-unroll",
      "round": 1,
      "prefix": [
        "licm"
      ],
      "reads_after_prefix": [
        "inst:Bubble:%11",
        "inst:Bubble:%13",
        "inst:Bubble:%14",
        "inst:Bubble:%15",
        "inst:Bubble:%17",
        "inst:Bubble:%18",
        "inst:Bubble:%21",
        "inst:Bubble:%22",
        "inst:Bubble:%23",
        "inst:Bubble:%24",
        "inst:Bubble:%25",
        "inst:Bubble:%3",
        "inst:Bubble:%4",
        "inst:Bubble:%5",
        "inst:Bubble:%6",
        "inst:Bubble:%7",
        "inst:Bubble:%exitcond",
        "inst:Bubble:.preheader:1:br",
        "inst:Bubble:bb2:1:br",
        "inst:Bubble:bb3:1:br",
        "inst:Bubble:bb4:1:store",
        "inst:Bubble:bb4:2:br",
        "inst:Bubble:bb5:1:br",
        "inst:Bubble:bb6:1:br",
        "inst:Bubble:bb7:1:ret",
        "loop:Bubble:.preheader",
        "loop:Bubble:bb0"
      ],
      "writes_after_prefix": [
        "bb:Bubble:.epil.preheader",
        "bb:Bubble:.epilog-lcssa",
        "bb:Bubble:.preheader.new",
        "bb:Bubble:.unr-lcssa",
        "bb:Bubble:bb10",
        "bb:Bubble:bb11",
        "bb:Bubble:bb8",
        "bb:Bubble:bb9",
        "inst:Bubble:%10",
        "inst:Bubble:%11",
        "inst:Bubble:%13",
        "inst:Bubble:%14",
        "inst:Bubble:%15",
        "inst:Bubble:%16",
        "inst:Bubble:%17",
        "inst:Bubble:%18",
        "inst:Bubble:%2",
        "inst:Bubble:%21",
        "inst:Bubble:%22",
        "inst:Bubble:%23",
        "inst:Bubble:%24",
        "inst:Bubble:%25",
        "inst:Bubble:%26",
        "inst:Bubble:%29",
        "inst:Bubble:%3",
        "inst:Bubble:%31",
        "inst:Bubble:%32",
        "inst:Bubble:%33",
        "inst:Bubble:%35",
        "inst:Bubble:%36",
        "inst:Bubble:%39",
        "inst:Bubble:%4",
        "inst:Bubble:%40",
        "inst:Bubble:%41",
        "inst:Bubble:%42",
        "inst:Bubble:%43",
        "inst:Bubble:%5",
        "inst:Bubble:%6",
        "inst:Bubble:%7",
        "inst:Bubble:%8",
        "inst:Bubble:%9",
        "inst:Bubble:%exitcond",
        "inst:Bubble:%indvar",
        "inst:Bubble:%indvar.next",
        "inst:Bubble:%indvars.iv.next.1",
        "inst:Bubble:%indvars.iv.next.epil",
        "inst:Bubble:%indvars.iv1.epil.init",
        "inst:Bubble:%indvars.iv1.unr",
        "inst:Bubble:%lcmp.mod",
        "inst:Bubble:%lcmp.mod1",
        "inst:Bubble:%niter",
        "inst:Bubble:%niter.ncmp.1",
        "inst:Bubble:%niter.next.1",
        "inst:Bubble:%unroll_iter",
        "inst:Bubble:%xtraiter",
        "inst:Bubble:.epil.preheader:1:call",
        "inst:Bubble:.epil.preheader:2:br",
        "inst:Bubble:.epilog-lcssa:1:br",
        "inst:Bubble:.preheader.new:1:br",
        "inst:Bubble:.preheader:1:br",
        "inst:Bubble:.unr-lcssa:1:br",
        "inst:Bubble:bb10:1:br",
        "inst:Bubble:bb11:1:ret",
        "inst:Bubble:bb2:1:br",
        "inst:Bubble:bb3:1:br",
        "inst:Bubble:bb3:1:store",
        "inst:Bubble:bb3:2:store",
        "inst:Bubble:bb3:3:br",
        "inst:Bubble:bb4:1:br",
        "inst:Bubble:bb4:1:store",
        "inst:Bubble:bb4:2:br",
        "inst:Bubble:bb5:1:br",
        "inst:Bubble:bb6:1:br",
        "inst:Bubble:bb7:1:ret",
        "inst:Bubble:bb7:1:store",
        "inst:Bubble:bb7:2:store",
        "inst:Bubble:bb7:3:br",
        "inst:Bubble:bb8:1:store",
        "inst:Bubble:bb8:2:br",
        "inst:Bubble:bb9:1:br",
        "loop:Bubble:.preheader",
        "loop:Bubble:bb0"
      ],
      "new_writes_after_prefix": [
        "inst:Bubble:%13",
        "inst:Bubble:%31"
      ],
      "changed_writes_after_prefix": [
        "inst:Bubble:%29"
      ]
    },
    {
      "edge_kind": "expansion",
      "enabler": "indvars",
      "enabled": "gvn",
      "round": 1,
      "prefix": [
        "indvars"
      ],
      "reads_after_prefix": [
        "inst:Bubble:%11",
        "inst:Bubble:%13",
        "inst:Bubble:%14",
        "inst:Bubble:%16",
        "inst:Bubble:%17",
        "inst:Bubble:%20",
        "inst:Bubble:%21",
        "inst:Bubble:%22",
        "inst:Bubble:%23",
        "inst:Bubble:%24",
        "inst:Bubble:%3",
        "inst:Bubble:%4"
      ],
      "writes_after_prefix": [
        "inst:Bubble:%.pre",
        "inst:Bubble:%10",
        "inst:Bubble:%11",
        "inst:Bubble:%12",
        "inst:Bubble:%13",
        "inst:Bubble:%14",
        "inst:Bubble:%15",
        "inst:Bubble:%16",
        "inst:Bubble:%17",
        "inst:Bubble:%18",
        "inst:Bubble:%20",
        "inst:Bubble:%21",
        "inst:Bubble:%22",
        "inst:Bubble:%23",
        "inst:Bubble:%24",
        "inst:Bubble:%25",
        "inst:Bubble:%3",
        "inst:Bubble:%4"
      ],
      "new_writes_after_prefix": [
        "inst:Bubble:%20"
      ],
      "changed_writes_after_prefix": [
        "inst:Bubble:%12",
        "inst:Bubble:%13",
        "inst:Bubble:%14",
        "inst:Bubble:%15",
        "inst:Bubble:%16",
        "inst:Bubble:%17",
        "inst:Bubble:%18",
        "inst:Bubble:%21",
        "inst:Bubble:%22",
        "inst:Bubble:%23",
        "inst:Bubble:%24",
        "inst:Bubble:%25"
      ]
    },
    {
      "edge_kind": "expansion",
      "enabler": "indvars",
      "enabled": "loop-unroll",
      "round": 1,
      "prefix": [
        "indvars"
      ],
      "reads_after_prefix": [
        "inst:Bubble:%11",
        "inst:Bubble:%13",
        "inst:Bubble:%14",
        "inst:Bubble:%16",
        "inst:Bubble:%17",
        "inst:Bubble:%20",
        "inst:Bubble:%21",
        "inst:Bubble:%22",
        "inst:Bubble:%24",
        "inst:Bubble:%3",
        "inst:Bubble:%4",
        "inst:Bubble:%5",
        "inst:Bubble:%6",
        "inst:Bubble:%7",
        "inst:Bubble:%exitcond",
        "inst:Bubble:.preheader:1:br",
        "inst:Bubble:bb2:1:br",
        "inst:Bubble:bb3:1:br",
        "inst:Bubble:bb4:1:store",
        "inst:Bubble:bb4:2:br",
        "inst:Bubble:bb5:1:br",
        "inst:Bubble:bb6:1:br",
        "inst:Bubble:bb7:1:ret",
        "loop:Bubble:.preheader",
        "loop:Bubble:bb0"
      ],
      "writes_after_prefix": [
        "bb:Bubble:.epil.preheader",
        "bb:Bubble:.epilog-lcssa",
        "bb:Bubble:.preheader.new",
        "bb:Bubble:.unr-lcssa",
        "bb:Bubble:bb10",
        "bb:Bubble:bb11",
        "bb:Bubble:bb8",
        "bb:Bubble:bb9",
        "inst:Bubble:%10",
        "inst:Bubble:%11",
        "inst:Bubble:%13",
        "inst:Bubble:%14",
        "inst:Bubble:%15",
        "inst:Bubble:%16",
        "inst:Bubble:%17",
        "inst:Bubble:%18",
        "inst:Bubble:%2",
        "inst:Bubble:%20",
        "inst:Bubble:%21",
        "inst:Bubble:%22",
        "inst:Bubble:%24",
        "inst:Bubble:%25",
        "inst:Bubble:%26",
        "inst:Bubble:%29",
        "inst:Bubble:%3",
        "inst:Bubble:%31",
        "inst:Bubble:%32",
        "inst:Bubble:%34",
        "inst:Bubble:%35",
        "inst:Bubble:%38",
        "inst:Bubble:%39",
        "inst:Bubble:%4",
        "inst:Bubble:%40",
        "inst:Bubble:%41",
        "inst:Bubble:%42",
        "inst:Bubble:%5",
        "inst:Bubble:%6",
        "inst:Bubble:%7",
        "inst:Bubble:%8",
        "inst:Bubble:%9",
        "inst:Bubble:%exitcond",
        "inst:Bubble:%indvar",
        "inst:Bubble:%indvar.next",
        "inst:Bubble:%indvars.iv.next.1",
        "inst:Bubble:%indvars.iv.next.epil",
        "inst:Bubble:%indvars.iv1.epil.init",
        "inst:Bubble:%indvars.iv1.unr",
        "inst:Bubble:%lcmp.mod",
        "inst:Bubble:%lcmp.mod1",
        "inst:Bubble:%niter",
        "inst:Bubble:%niter.ncmp.1",
        "inst:Bubble:%niter.next.1",
        "inst:Bubble:%unroll_iter",
        "inst:Bubble:%xtraiter",
        "inst:Bubble:.epil.preheader:1:call",
        "inst:Bubble:.epil.preheader:2:br",
        "inst:Bubble:.epilog-lcssa:1:br",
        "inst:Bubble:.preheader.new:1:br",
        "inst:Bubble:.preheader:1:br",
        "inst:Bubble:.unr-lcssa:1:br",
        "inst:Bubble:bb10:1:br",
        "inst:Bubble:bb11:1:ret",
        "inst:Bubble:bb2:1:br",
        "inst:Bubble:bb3:1:br",
        "inst:Bubble:bb3:1:store",
        "inst:Bubble:bb3:2:store",
        "inst:Bubble:bb3:3:br",
        "inst:Bubble:bb4:1:br",
        "inst:Bubble:bb4:1:store",
        "inst:Bubble:bb4:2:br",
        "inst:Bubble:bb5:1:br",
        "inst:Bubble:bb6:1:br",
        "inst:Bubble:bb7:1:ret",
        "inst:Bubble:bb7:1:store",
        "inst:Bubble:bb7:2:store",
        "inst:Bubble:bb7:3:br",
        "inst:Bubble:bb8:1:store",
        "inst:Bubble:bb8:2:br",
        "inst:Bubble:bb9:1:br",
        "loop:Bubble:.preheader",
        "loop:Bubble:bb0"
      ],
      "new_writes_after_prefix": [
        "inst:Bubble:%13",
        "inst:Bubble:%20",
        "inst:Bubble:%31",
        "inst:Bubble:%34",
        "inst:Bubble:%38"
      ],
      "changed_writes_after_prefix": [
        "inst:Bubble:%29",
        "inst:Bubble:%32",
        "inst:Bubble:%35",
        "inst:Bubble:%39",
        "inst:Bubble:%40",
        "inst:Bubble:%41",
        "inst:Bubble:%42",
        "inst:Bubble:bb8:1:store"
      ]
    },
    {
      "edge_kind": "expansion",
      "enabler": "loop-unroll",
      "enabled": "instcombine",
      "round": 1,
      "prefix": [
        "loop-unroll"
      ],
      "reads_after_prefix": [
        "inst:Bubble:%.lcssa",
        "inst:Bubble:%10",
        "inst:Bubble:%11",
        "inst:Bubble:%16",
        "inst:Bubble:%17",
        "inst:Bubble:%18",
        "inst:Bubble:%2",
        "inst:Bubble:%23",
        "inst:Bubble:%24",
        "inst:Bubble:%25",
        "inst:Bubble:%26",
        "inst:Bubble:%29",
        "inst:Bubble:%3",
        "inst:Bubble:%30",
        "inst:Bubble:%32",
        "inst:Bubble:%33",
        "inst:Bubble:%35",
        "inst:Bubble:%36",
        "inst:Bubble:%39",
        "inst:Bubble:%4",
        "inst:Bubble:%40",
        "inst:Bubble:%41",
        "inst:Bubble:%42",
        "inst:Bubble:%43",
        "inst:Bubble:%5",
        "inst:Bubble:%9",
        "inst:Bubble:%indvars.iv.next.epil",
        "inst:Bubble:%indvars.iv1.unr",
        "inst:Bubble:%indvars.iv22",
        "inst:Bubble:%lcmp.mod",
        "inst:Bubble:%lcmp.mod1",
        "inst:Bubble:%niter.ncmp.1",
        "inst:Bubble:%unroll_iter",
        "inst:bInitarr:%exitcond",
        "inst:main:%exitcond",
        "loop:Bubble:bb0",
        "loop:bInitarr:bb0",
        "loop:main:bb0"
      ],
      "writes_after_prefix": [
        "inst:Bubble:%.lcssa",
        "inst:Bubble:%10",
        "inst:Bubble:%11",
        "inst:Bubble:%12",
        "inst:Bubble:%13",
        "inst:Bubble:%16",
        "inst:Bubble:%17",
        "inst:Bubble:%18",
        "inst:Bubble:%2",
        "inst:Bubble:%20",
        "inst:Bubble:%21",
        "inst:Bubble:%23",
        "inst:Bubble:%24",
        "inst:Bubble:%25",
        "inst:Bubble:%26",
        "inst:Bubble:%28",
        "inst:Bubble:%29",
        "inst:Bubble:%3",
        "inst:Bubble:%30",
        "inst:Bubble:%31",
        "inst:Bubble:%32",
        "inst:Bubble:%33",
        "inst:Bubble:%34",
        "inst:Bubble:%35",
        "inst:Bubble:%36",
        "inst:Bubble:%38",
        "inst:Bubble:%39",
        "inst:Bubble:%4",
        "inst:Bubble:%40",
        "inst:Bubble:%41",
        "inst:Bubble:%42",
        "inst:Bubble:%43",
        "inst:Bubble:%5",
        "inst:Bubble:%6",
        "inst:Bubble:%9",
        "inst:Bubble:%indvars.iv.next.epil",
        "inst:Bubble:%indvars.iv1.unr",
        "inst:Bubble:%indvars.iv22",
        "inst:Bubble:%lcmp.mod",
        "inst:Bubble:%lcmp.mod.not",
        "inst:Bubble:%lcmp.mod1",
        "inst:Bubble:%niter.ncmp.1",
        "inst:Bubble:%niter.ncmp.1.not",
        "inst:Bubble:%unroll_iter",
        "inst:bInitarr:%exitcond",
        "inst:bInitarr:%exitcond.not",
        "inst:main:%exitcond",
        "inst:main:%exitcond.not",
        "loop:Bubble:.unr-lcssa",
        "loop:Bubble:bb0",
        "loop:bInitarr:bb0",
        "loop:bInitarr:bb5",
        "loop:main:bb0",
        "loop:main:bb1"
      ],
      "new_writes_after_prefix": [
        "inst:Bubble:%10",
        "inst:Bubble:%16",
        "inst:Bubble:%17",
        "inst:Bubble:%18",
        "inst:Bubble:%2",
        "inst:Bubble:%20",
        "inst:Bubble:%21",
        "inst:Bubble:%23",
        "inst:Bubble:%24",
        "inst:Bubble:%25",
        "inst:Bubble:%26",
        "inst:Bubble:%28",
        "inst:Bubble:%29",
        "inst:Bubble:%3",
        "inst:Bubble:%30",
        "inst:Bubble:%31",
        "inst:Bubble:%32",
        "inst:Bubble:%33",
        "inst:Bubble:%34",
        "inst:Bubble:%35",
        "inst:Bubble:%36",
        "inst:Bubble:%38",
        "inst:Bubble:%39",
        "inst:Bubble:%4",
        "inst:Bubble:%40",
        "inst:Bubble:%41",
        "inst:Bubble:%42",
        "inst:Bubble:%43",
        "inst:Bubble:%5",
        "inst:Bubble:%6",
        "inst:Bubble:%9",
        "inst:Bubble:%indvars.iv.next.epil",
        "inst:Bubble:%indvars.iv1.unr",
        "inst:Bubble:%indvars.iv22",
        "inst:Bubble:%lcmp.mod",
        "inst:Bubble:%lcmp.mod.not",
        "inst:Bubble:%lcmp.mod1",
        "inst:Bubble:%niter.ncmp.1",
        "inst:Bubble:%niter.ncmp.1.not",
        "inst:Bubble:%unroll_iter",
        "loop:Bubble:.unr-lcssa"
      ],
      "changed_writes_after_prefix": [
        "inst:Bubble:%11",
        "inst:Bubble:%12",
        "inst:Bubble:%13"
      ]
    },
    {
      "edge_kind": "activation",
      "enabler": "loop-unroll",
      "enabled": "simplifycfg",
      "round": 1,
      "prefix": [
        "loop-unroll"
      ],
      "reads_after_prefix": [
        "bb:Bubble:bb10",
        "bb:Bubble:bb11",
        "inst:Bubble:%22",
        "inst:Bubble:%23",
        "inst:Bubble:%24",
        "inst:Bubble:%25",
        "inst:Bubble:%26",
        "inst:Bubble:%29",
        "inst:Bubble:%30",
        "inst:Bubble:%32",
        "inst:Bubble:%33",
        "inst:Bubble:%35",
        "inst:Bubble:%36",
        "inst:Bubble:%39",
        "inst:Bubble:%40",
        "inst:Bubble:%41",
        "inst:Bubble:%42",
        "inst:Bubble:%43",
        "inst:Bubble:.epil.preheader:2:br",
        "inst:Bubble:.epilog-lcssa:1:br",
        "inst:Bubble:bb10:1:br",
        "inst:Bubble:bb11:1:ret",
        "inst:Bubble:bb5:1:br",
        "inst:Bubble:bb6:1:br",
        "inst:Bubble:bb7:1:store",
        "inst:Bubble:bb7:2:store",
        "inst:Bubble:bb7:3:br",
        "inst:Bubble:bb8:1:store",
        "inst:Bubble:bb8:2:br",
        "inst:Bubble:bb9:1:br",
        "loop:Bubble:.preheader"
      ],
      "writes_after_prefix": [
        "bb:Bubble:bb10",
        "bb:Bubble:bb11",
        "inst:Bubble:%21",
        "inst:Bubble:%22",
        "inst:Bubble:%23",
        "inst:Bubble:%24",
        "inst:Bubble:%25",
        "inst:Bubble:%26",
        "inst:Bubble:%27",
        "inst:Bubble:%28",
        "inst:Bubble:%29",
        "inst:Bubble:%30",
        "inst:Bubble:%31",
        "inst:Bubble:%32",
        "inst:Bubble:%33",
        "inst:Bubble:%34",
        "inst:Bubble:%35",
        "inst:Bubble:%36",
        "inst:Bubble:%37",
        "inst:Bubble:%38",
        "inst:Bubble:%39",
        "inst:Bubble:%40",
        "inst:Bubble:%41",
        "inst:Bubble:%42",
        "inst:Bubble:%43",
        "inst:Bubble:.epil.preheader:2:br",
        "inst:Bubble:.epilog-lcssa:1:br",
        "inst:Bubble:bb10:1:br",
        "inst:Bubble:bb11:1:ret",
        "inst:Bubble:bb5:1:br",
        "inst:Bubble:bb5:1:store",
        "inst:Bubble:bb5:2:store",
        "inst:Bubble:bb5:3:br",
        "inst:Bubble:bb6:1:br",
        "inst:Bubble:bb6:1:store",
        "inst:Bubble:bb6:2:br",
        "inst:Bubble:bb7:1:br",
        "inst:Bubble:bb7:1:store",
        "inst:Bubble:bb7:2:store",
        "inst:Bubble:bb7:3:br",
        "inst:Bubble:bb8:1:br",
        "inst:Bubble:bb8:1:store",
        "inst:Bubble:bb8:2:br",
        "inst:Bubble:bb9:1:br",
        "inst:Bubble:bb9:1:ret",
        "loop:Bubble:.preheader"
      ],
      "new_writes_after_prefix": [
        "bb:Bubble:bb10",
        "bb:Bubble:bb11",
        "inst:Bubble:%21",
        "inst:Bubble:%22",
        "inst:Bubble:%23",
        "inst:Bubble:%24",
        "inst:Bubble:%25",
        "inst:Bubble:%26",
        "inst:Bubble:%27",
        "inst:Bubble:%28",
        "inst:Bubble:%29",
        "inst:Bubble:%30",
        "inst:Bubble:%31",
        "inst:Bubble:%32",
        "inst:Bubble:%33",
        "inst:Bubble:%34",
        "inst:Bubble:%35",
        "inst:Bubble:%36",
        "inst:Bubble:%37",
        "inst:Bubble:%38",
        "inst:Bubble:%39",
        "inst:Bubble:%40",
        "inst:Bubble:%41",
        "inst:Bubble:%42",
        "inst:Bubble:%43",
        "inst:Bubble:.epil.preheader:2:br",
        "inst:Bubble:.epilog-lcssa:1:br",
        "inst:Bubble:bb10:1:br",
        "inst:Bubble:bb11:1:ret",
        "inst:Bubble:bb5:1:br",
        "inst:Bubble:bb5:1:store",
        "inst:Bubble:bb5:2:store",
        "inst:Bubble:bb5:3:br",
        "inst:Bubble:bb6:1:br",
        "inst:Bubble:bb6:1:store",
        "inst:Bubble:bb6:2:br",
        "inst:Bubble:bb7:1:br",
        "inst:Bubble:bb7:1:store",
        "inst:Bubble:bb7:2:store",
        "inst:Bubble:bb7:3:br",
        "inst:Bubble:bb8:1:br",
        "inst:Bubble:bb8:1:store",
        "inst:Bubble:bb8:2:br",
        "inst:Bubble:bb9:1:br",
        "inst:Bubble:bb9:1:ret",
        "loop:Bubble:.preheader"
      ],
      "changed_writes_after_prefix": []
    },
    {
      "edge_kind": "expansion",
      "enabler": "loop-unroll",
      "enabled": "early-cse",
      "round": 1,
      "prefix": [
        "loop-unroll"
      ],
      "reads_after_prefix": [
        "inst:Bubble:%.lcssa",
        "inst:Bubble:%14",
        "inst:Bubble:%15",
        "inst:Bubble:%16",
        "inst:Bubble:%17",
        "inst:Bubble:%18",
        "inst:Bubble:%22",
        "inst:Bubble:%23",
        "inst:Bubble:%24",
        "inst:Bubble:%25",
        "inst:Bubble:%26",
        "inst:Bubble:%29",
        "inst:Bubble:%30",
        "inst:Bubble:%32",
        "inst:Bubble:%33",
        "inst:Bubble:%35",
        "inst:Bubble:%36",
        "inst:Bubble:%39",
        "inst:Bubble:%40",
        "inst:Bubble:%41",
        "inst:Bubble:%42",
        "inst:Bubble:%43",
        "inst:Bubble:%indvars.iv1.unr"
      ],
      "writes_after_prefix": [
        "inst:Bubble:%.lcssa",
        "inst:Bubble:%14",
        "inst:Bubble:%15",
        "inst:Bubble:%16",
        "inst:Bubble:%17",
        "inst:Bubble:%18",
        "inst:Bubble:%21",
        "inst:Bubble:%22",
        "inst:Bubble:%23",
        "inst:Bubble:%24",
        "inst:Bubble:%25",
        "inst:Bubble:%26",
        "inst:Bubble:%28",
        "inst:Bubble:%29",
        "inst:Bubble:%30",
        "inst:Bubble:%31",
        "inst:Bubble:%32",
        "inst:Bubble:%33",
        "inst:Bubble:%34",
        "inst:Bubble:%35",
        "inst:Bubble:%36",
        "inst:Bubble:%38",
        "inst:Bubble:%39",
        "inst:Bubble:%40",
        "inst:Bubble:%41",
        "inst:Bubble:%42",
        "inst:Bubble:%43",
        "inst:Bubble:%indvars.iv1.unr"
      ],
      "new_writes_after_prefix": [
        "inst:Bubble:%14",
        "inst:Bubble:%15",
        "inst:Bubble:%16",
        "inst:Bubble:%17",
        "inst:Bubble:%18",
        "inst:Bubble:%21",
        "inst:Bubble:%22",
        "inst:Bubble:%23",
        "inst:Bubble:%24",
        "inst:Bubble:%25",
        "inst:Bubble:%26",
        "inst:Bubble:%28",
        "inst:Bubble:%29",
        "inst:Bubble:%30",
        "inst:Bubble:%31",
        "inst:Bubble:%32",
        "inst:Bubble:%33",
        "inst:Bubble:%34",
        "inst:Bubble:%35",
        "inst:Bubble:%36",
        "inst:Bubble:%38",
        "inst:Bubble:%39",
        "inst:Bubble:%40",
        "inst:Bubble:%41",
        "inst:Bubble:%42",
        "inst:Bubble:%43",
        "inst:Bubble:%indvars.iv1.unr"
      ],
      "changed_writes_after_prefix": []
    },
    {
      "edge_kind": "expansion",
      "enabler": "loop-unroll",
      "enabled": "gvn",
      "round": 1,
      "prefix": [
        "loop-unroll"
      ],
      "reads_after_prefix": [
        "bb:Bubble:bb11",
        "inst:Bubble:%.lcssa",
        "inst:Bubble:%14",
        "inst:Bubble:%15",
        "inst:Bubble:%16",
        "inst:Bubble:%17",
        "inst:Bubble:%18",
        "inst:Bubble:%23",
        "inst:Bubble:%24",
        "inst:Bubble:%25",
        "inst:Bubble:%26",
        "inst:Bubble:%29",
        "inst:Bubble:%30",
        "inst:Bubble:%32",
        "inst:Bubble:%33",
        "inst:Bubble:%35",
        "inst:Bubble:%36",
        "inst:Bubble:%39",
        "inst:Bubble:%40",
        "inst:Bubble:%41",
        "inst:Bubble:%42",
        "inst:Bubble:%43",
        "inst:Bubble:%7",
        "inst:Bubble:%8",
        "inst:Bubble:%indvars.iv1.unr",
        "inst:Bubble:.epil.preheader:2:br",
        "inst:Bubble:bb10:1:br",
        "inst:Bubble:bb11:1:ret",
        "inst:Bubble:bb6:1:br",
        "inst:Bubble:bb7:1:store",
        "inst:Bubble:bb7:2:store",
        "inst:Bubble:bb7:3:br",
        "inst:Bubble:bb8:1:store",
        "inst:Bubble:bb8:2:br",
        "inst:Bubble:bb9:1:br"
      ],
      "writes_after_prefix": [
        "bb:Bubble:.preheader..epil.preheader_crit_edge",
        "bb:Bubble:bb11",
        "inst:Bubble:%.lcssa",
        "inst:Bubble:%.pre",
        "inst:Bubble:%.pre2",
        "inst:Bubble:%14",
        "inst:Bubble:%15",
        "inst:Bubble:%16",
        "inst:Bubble:%17",
        "inst:Bubble:%18",
        "inst:Bubble:%20",
        "inst:Bubble:%21",
        "inst:Bubble:%23",
        "inst:Bubble:%24",
        "inst:Bubble:%25",
        "inst:Bubble:%26",
        "inst:Bubble:%28",
        "inst:Bubble:%29",
        "inst:Bubble:%30",
        "inst:Bubble:%31",
        "inst:Bubble:%32",
        "inst:Bubble:%33",
        "inst:Bubble:%34",
        "inst:Bubble:%35",
        "inst:Bubble:%36",
        "inst:Bubble:%38",
        "inst:Bubble:%39",
        "inst:Bubble:%40",
        "inst:Bubble:%41",
        "inst:Bubble:%42",
        "inst:Bubble:%43",
        "inst:Bubble:%7",
        "inst:Bubble:%8",
        "inst:Bubble:%indvars.iv1.unr",
        "inst:Bubble:.epil.preheader:2:br",
        "inst:Bubble:.preheader..epil.preheader_crit_edge:1:br",
        "inst:Bubble:bb10:1:br",
        "inst:Bubble:bb10:1:ret",
        "inst:Bubble:bb11:1:ret",
        "inst:Bubble:bb6:1:br",
        "inst:Bubble:bb6:1:store",
        "inst:Bubble:bb6:2:store",
        "inst:Bubble:bb6:3:br",
        "inst:Bubble:bb7:1:store",
        "inst:Bubble:bb7:2:br",
        "inst:Bubble:bb7:2:store",
        "inst:Bubble:bb7:3:br",
        "inst:Bubble:bb8:1:br",
        "inst:Bubble:bb8:1:store",
        "inst:Bubble:bb8:2:br",
        "inst:Bubble:bb9:1:br"
      ],
      "new_writes_after_prefix": [
        "bb:Bubble:.preheader..epil.preheader_crit_edge",
        "bb:Bubble:bb11",
        "inst:Bubble:%.pre2",
        "inst:Bubble:%20",
        "inst:Bubble:%28",
        "inst:Bubble:%29",
        "inst:Bubble:%30",
        "inst:Bubble:%31",
        "inst:Bubble:%32",
        "inst:Bubble:%33",
        "inst:Bubble:%34",
        "inst:Bubble:%35",
        "inst:Bubble:%36",
        "inst:Bubble:%38",
        "inst:Bubble:%39",
        "inst:Bubble:%40",
        "inst:Bubble:%41",
        "inst:Bubble:%42",
        "inst:Bubble:%43",
        "inst:Bubble:%7",
        "inst:Bubble:%8",
        "inst:Bubble:%indvars.iv1.unr",
        "inst:Bubble:.epil.preheader:2:br",
        "inst:Bubble:.preheader..epil.preheader_crit_edge:1:br",
        "inst:Bubble:bb10:1:br",
        "inst:Bubble:bb10:1:ret",
        "inst:Bubble:bb11:1:ret",
        "inst:Bubble:bb6:1:br",
        "inst:Bubble:bb6:1:store",
        "inst:Bubble:bb6:2:store",
        "inst:Bubble:bb6:3:br",
        "inst:Bubble:bb7:1:store",
        "inst:Bubble:bb7:2:br",
        "inst:Bubble:bb7:2:store",
        "inst:Bubble:bb7:3:br",
        "inst:Bubble:bb8:1:br",
        "inst:Bubble:bb8:1:store",
        "inst:Bubble:bb8:2:br",
        "inst:Bubble:bb9:1:br"
      ],
      "changed_writes_after_prefix": [
        "inst:Bubble:%14",
        "inst:Bubble:%15",
        "inst:Bubble:%16",
        "inst:Bubble:%17",
        "inst:Bubble:%18",
        "inst:Bubble:%21",
        "inst:Bubble:%23",
        "inst:Bubble:%24",
        "inst:Bubble:%25",
        "inst:Bubble:%26"
      ]
    },
    {
      "edge_kind": "expansion",
      "enabler": "loop-unroll",
      "enabled": "licm",
      "round": 1,
      "prefix": [
        "loop-unroll"
      ],
      "reads_after_prefix": [
        "inst:Bubble:%.lcssa",
        "inst:Bubble:%29",
        "inst:Bubble:%30"
      ],
      "writes_after_prefix": [
        "inst:Bubble:%.lcssa",
        "inst:Bubble:%29",
        "inst:Bubble:%30",
        "inst:Bubble:%31",
        "inst:Bubble:%indvars.iv.next3.lcssa"
      ],
      "new_writes_after_prefix": [
        "inst:Bubble:%29",
        "inst:Bubble:%30",
        "inst:Bubble:%31"
      ],
      "changed_writes_after_prefix": []
    },
    {
      "edge_kind": "expansion",
      "enabler": "loop-unroll",
      "enabled": "indvars",
      "round": 1,
      "prefix": [
        "loop-unroll"
      ],
      "reads_after_prefix": [
        "inst:Bubble:%.lcssa",
        "inst:Bubble:%29",
        "inst:Bubble:%3",
        "inst:Bubble:%30",
        "inst:Bubble:%32",
        "inst:Bubble:%33",
        "inst:Bubble:%35",
        "inst:Bubble:%36",
        "inst:Bubble:%39",
        "inst:Bubble:%4",
        "inst:Bubble:%40",
        "inst:Bubble:%41",
        "inst:Bubble:%42",
        "inst:Bubble:%43",
        "inst:Bubble:%5",
        "inst:Bubble:%indvar.next",
        "inst:Bubble:%indvars.iv.next3",
        "inst:Bubble:%indvars.iv22",
        "inst:Bubble:bb8:1:store"
      ],
      "writes_after_prefix": [
        "inst:Bubble:%.lcssa",
        "inst:Bubble:%29",
        "inst:Bubble:%3",
        "inst:Bubble:%30",
        "inst:Bubble:%31",
        "inst:Bubble:%32",
        "inst:Bubble:%33",
        "inst:Bubble:%34",
        "inst:Bubble:%35",
        "inst:Bubble:%36",
        "inst:Bubble:%37",
        "inst:Bubble:%38",
        "inst:Bubble:%39",
        "inst:Bubble:%4",
        "inst:Bubble:%40",
        "inst:Bubble:%41",
        "inst:Bubble:%42",
        "inst:Bubble:%43",
        "inst:Bubble:%5",
        "inst:Bubble:%exitcond",
        "inst:Bubble:%indvar.next",
        "inst:Bubble:%indvars.iv.next3",
        "inst:Bubble:%indvars.iv22",
        "inst:Bubble:bb8:1:store"
      ],
      "new_writes_after_prefix": [
        "inst:Bubble:%29",
        "inst:Bubble:%3",
        "inst:Bubble:%30",
        "inst:Bubble:%31",
        "inst:Bubble:%32",
        "inst:Bubble:%33",
        "inst:Bubble:%34",
        "inst:Bubble:%35",
        "inst:Bubble:%36",
        "inst:Bubble:%37",
        "inst:Bubble:%38",
        "inst:Bubble:%39",
        "inst:Bubble:%4",
        "inst:Bubble:%40",
        "inst:Bubble:%41",
        "inst:Bubble:%42",
        "inst:Bubble:%43",
        "inst:Bubble:%5",
        "inst:Bubble:%exitcond",
        "inst:Bubble:%indvar.next",
        "inst:Bubble:%indvars.iv.next3",
        "inst:Bubble:%indvars.iv22",
        "inst:Bubble:bb8:1:store"
      ],
      "changed_writes_after_prefix": []
    }
  ]
}
